ntt_3_tfdg_full_twiddle_4_2_sum_axi_5/ntt_1/ntt_1.srcs/sources_1/ntt_ip/ip/src/PE/Reconfigurable Butterfly Unit/winograd_pre_transform.sv
// ============================================================================
// 文件名: winograd_pre_transform.v
// 描述: Winograd预变换模块，实现对称分组优化
// 创新点: 将高基数蝶形分解为对称组，减少乘法次数
// ============================================================================
module winograd_pre_transform #(
    parameter MAX_WIDTH = 384,
    parameter MAX_RADIX = 16,
    parameter NUM_CORES = 8
)(
    // 系统接口
    input wire clk,
    input wire rst_n,
    input wire start,
    
    // 配置
    input wire [1:0] radix_mode,
    
    // 原始输入
    input wire [MAX_WIDTH-1:0] data_in [0:MAX_RADIX-1],
    input wire [MAX_WIDTH-1:0] twiddle_in [0:MAX_RADIX/2-1],
    input wire [MAX_WIDTH-1:0] modulus,
    
    // 预变换输出（每个子核的输入）
    output reg [MAX_WIDTH-1:0] x0_out [0:NUM_CORES-1],
    output reg [MAX_WIDTH-1:0] x1_out [0:NUM_CORES-1],
    output reg [MAX_WIDTH-1:0] w_out [0:NUM_CORES-1],
    output reg [MAX_WIDTH-1:0] conj_coeff_out [0:NUM_CORES-1],
    output reg valid_out
);

// ============================================================================
// 内部状态机
// ============================================================================
reg [2:0] state;
localparam [2:0]
    IDLE = 3'd0,
    CALC_GROUPS = 3'd1,
    APPLY_TRANSFORM = 3'd2,
    OUTPUT_READY = 3'd3;

// ============================================================================
// 根据基数进行对称分组
// ============================================================================
reg [MAX_WIDTH-1:0] group_x0 [0:7];  // 每组预变换后的x0
reg [MAX_WIDTH-1:0] group_x1 [0:7];  // 每组预变换后的x1
reg [MAX_WIDTH-1:0] group_w [0:7];   // 每组对应的旋转因子
reg [MAX_WIDTH-1:0] group_conj [0:7]; // 每组共轭系数

// 辅助函数：模加法（不使用%）
function automatic [MAX_WIDTH-1:0] mod_add;
    input [MAX_WIDTH-1:0] a;
    input [MAX_WIDTH-1:0] b;
    input [MAX_WIDTH-1:0] mod;
    reg [MAX_WIDTH:0] sum;  // 扩展1位用于检测溢出
    begin
        sum = a + b;
        if (sum >= mod) begin
            mod_add = sum - mod;
        end else begin
            mod_add = sum;
        end
    end
endfunction

// 辅助函数：模减法（不使用%）
function automatic [MAX_WIDTH-1:0] mod_sub;
    input [MAX_WIDTH-1:0] a;
    input [MAX_WIDTH-1:0] b;
    input [MAX_WIDTH-1:0] mod;
    reg [MAX_WIDTH-1:0] diff;
    begin
        if (a >= b) begin
            diff = a - b;
        end else begin
            diff = a + mod - b;  // 等价于 (a - b + mod)
        end
        // 确保结果在模范围内
        if (diff >= mod) begin
            diff = diff - mod;
        end
        mod_sub = diff;
    end
endfunction

// 辅助函数：模取反（用于计算a的模负数）
function automatic [MAX_WIDTH-1:0] mod_neg;
    input [MAX_WIDTH-1:0] a;
    input [MAX_WIDTH-1:0] mod;
    begin
        if (a == 0) begin
            mod_neg = 0;
        end else begin
            mod_neg = mod - a;
        end
    end
endfunction

always @(posedge clk or negedge rst_n) begin
    if (!rst_n) begin
        state <= IDLE;
        valid_out <= 1'b0;
        for (integer i = 0; i < NUM_CORES; i = i + 1) begin
            x0_out[i] <= {MAX_WIDTH{1'b0}};
            x1_out[i] <= {MAX_WIDTH{1'b0}};
            w_out[i] <= {MAX_WIDTH{1'b0}};
            conj_coeff_out[i] <= {MAX_WIDTH{1'b0}};
        end
    end else begin
        case(state)
            IDLE: begin
                if (start) begin
                    state <= CALC_GROUPS;
                    valid_out <= 1'b0;
                end
            end
            
            CALC_GROUPS: begin
                    case(radix_mode)
                        2'b00: begin  // 基2：不分组，直接使用
                            group_x0[0] <= data_in[0];
                            group_x1[0] <= data_in[1];
                            group_w[0] <= twiddle_in[0];
                            group_conj[0] <= {MAX_WIDTH{1'b0}};  // 基2无共轭
                        end
                        
                        2'b01: begin  // 基4：分为2组
                            // 组0: (w₀, w₃)，w₃是w₁的模逆
                            group_x0[0] <= mod_add(data_in[0], data_in[2], modulus);
                            group_x1[0] <= mod_add(data_in[1], data_in[3], modulus);
                            group_w[0] <= twiddle_in[0];  // w0
                            group_conj[0] <= calculate_conjugate(twiddle_in[1], modulus);  // w3
                            
                            // 组1: (w₁, w₂)，w₂是w₀的模逆
                            group_x0[1] <= mod_sub(data_in[0], data_in[2], modulus);
                            group_x1[1] <= mod_sub(data_in[1], data_in[3], modulus);
                            group_w[1] <= twiddle_in[1];  // w1
                            group_conj[1] <= calculate_conjugate(twiddle_in[0], modulus);  // w2
                        end
                        
                        2'b10: begin  // 基8：分为4组
                            for (integer g = 0; g < 4; g = g + 1) begin
                                integer idx1 = g;
                                integer idx2 = 7 - g;
                                
                                group_x0[g] <= mod_add(data_in[idx1], data_in[idx2], modulus);
                                group_x1[g] <= mod_sub(data_in[idx1], data_in[idx2], modulus);
                                group_w[g] <= twiddle_in[g];  // w0~w3
                                group_conj[g] <= calculate_conjugate(twiddle_in[g], modulus);  // w7~w4
                            end
                        end
                        
                        2'b11: begin  // 基16：分为8组
                            for (integer g = 0; g < 8; g = g + 1) begin
                                integer idx1 = g;
                                integer idx2 = 15 - g;
                                
                                group_x0[g] <= mod_add(data_in[idx1], data_in[idx2], modulus);
                                group_x1[g] <= mod_sub(data_in[idx1], data_in[idx2], modulus);
                                group_w[g] <= twiddle_in[g];  // w0~w7
                                group_conj[g] <= calculate_conjugate(twiddle_in[g], modulus);  // w15~w8
                            end
                        end
                    endcase
                    
                    state <= APPLY_TRANSFORM;
                end            
            APPLY_TRANSFORM: begin
                // 将分组结果分配给各子核
                for (integer i = 0; i < NUM_CORES; i = i + 1) begin
                    if (i < (1 << (radix_mode + 1)) / 2) begin  // 根据基数确定需要的组数
                        x0_out[i] <= group_x0[i];
                        x1_out[i] <= group_x1[i];
                        w_out[i] <= group_w[i];
                        conj_coeff_out[i] <= group_conj[i];
                    end else begin
                        // 多余的子核输入置零
                        x0_out[i] <= {MAX_WIDTH{1'b0}};
                        x1_out[i] <= {MAX_WIDTH{1'b0}};
                        w_out[i] <= {MAX_WIDTH{1'b0}};
                        conj_coeff_out[i] <= {MAX_WIDTH{1'b0}};
                    end
                end
                
                state <= OUTPUT_READY;
                valid_out <= 1'b1;
            end
            
            OUTPUT_READY: begin
                if (!start) begin
                    state <= IDLE;
                    valid_out <= 1'b0;
                end
            end
        endcase
    end
end

// ============================================================================
// 共轭计算函数
// ============================================================================
function automatic [MAX_WIDTH-1:0] calculate_conjugate;
    input [MAX_WIDTH-1:0] w;
    input [MAX_WIDTH-1:0] modulus;
    begin
        // 计算w的共轭（模逆）
        // 实际实现可能需要模逆运算或查表
        // 这里简化处理，实际应用中需要预计算
        calculate_conjugate = modular_inverse(w, modulus);
    end
endfunction

// 模逆函数（简化表示，实际需要实现或预计算）
function automatic [MAX_WIDTH-1:0] modular_inverse;
    input [MAX_WIDTH-1:0] a;
    input [MAX_WIDTH-1:0] modulus;
    reg [MAX_WIDTH-1:0] result;
    begin
        // 实际实现需要使用扩展欧几里得算法
        // 这里返回一个简化值
        modular_inverse = a;  // 简化处理
    end
endfunction


endmodule

NTT-accelerator-for-ZKP-0.4/ntt_3_tfdg_full_twiddle_4_2_sum_axi_5/sour/PE/Reconfigurable Butterfly Unit/winograd_pre_transform_tb.sv
`timescale 1ns/1ps

module winograd_pre_transform_tb;
    // 参数定义
    parameter MAX_WIDTH = 8;      // 简化测试，使用8位宽度
    parameter MAX_RADIX = 16;
    parameter NUM_CORES = 8;
    
    // 时钟和复位信号
    reg clk;
    reg rst_n;
    reg start;
    
    // 配置信号
    reg [1:0] radix_mode;
    
    // 输入数据
    reg [MAX_WIDTH-1:0] data_in [0:MAX_RADIX-1];
    reg [MAX_WIDTH-1:0] twiddle_in [0:MAX_RADIX/2-1];
    reg [MAX_WIDTH-1:0] modulus;
    
    // 输出信号
    wire [MAX_WIDTH-1:0] x0_out [0:NUM_CORES-1];
    wire [MAX_WIDTH-1:0] x1_out [0:NUM_CORES-1];
    wire [MAX_WIDTH-1:0] w_out [0:NUM_CORES-1];
    wire [MAX_WIDTH-1:0] conj_coeff_out [0:NUM_CORES-1];
    wire valid_out;
    
    // 实例化被测试模块
    winograd_pre_transform #(
        .MAX_WIDTH(MAX_WIDTH),
        .MAX_RADIX(MAX_RADIX),
        .NUM_CORES(NUM_CORES)
    ) dut (
        .clk(clk),
        .rst_n(rst_n),
        .start(start),
        .radix_mode(radix_mode),
        .data_in(data_in),
        .twiddle_in(twiddle_in),
        .modulus(modulus),
        .x0_out(x0_out),
        .x1_out(x1_out),
        .w_out(w_out),
        .conj_coeff_out(conj_coeff_out),
        .valid_out(valid_out)
    );
    
    // 生成时钟
    always #5 clk = ~clk;  // 100MHz时钟
    
    // 测试任务：初始化所有输入
    task init_inputs;
    begin
        start = 0;
        radix_mode = 0;
        modulus = 17;  // 使用质数17作为模数
        
        // 初始化数据输入
        for (integer i = 0; i < MAX_RADIX; i = i + 1) begin
            data_in[i] = i;  // 简单使用0-15作为输入
        end
        
        // 初始化旋转因子
        for (integer i = 0; i < MAX_RADIX/2; i = i + 1) begin
            twiddle_in[i] = (i + 1) % modulus;  // 简单旋转因子
        end
    end
    endtask
    
    // 测试任务：打印输出结果
    task print_outputs;
    input integer test_num;
    begin
        $display("=== Test %0d Outputs ===", test_num);
        $display("Valid: %b", valid_out);
        
        for (integer i = 0; i < NUM_CORES; i = i + 1) begin
            if (x0_out[i] != 0 || x1_out[i] != 0 || w_out[i] != 0 || conj_coeff_out[i] != 0) begin
                $display("Core %0d: x0=%h, x1=%h, w=%h, conj=%h", 
                         i, x0_out[i], x1_out[i], w_out[i], conj_coeff_out[i]);
            end
        end
        $display("");
    end
    endtask
    
    // 测试任务：执行一次变换
    task run_test;
    input [1:0] mode;
    input string mode_name;
    begin
        $display("\n=== Testing %s Mode ===", mode_name);
        
        // 设置模式
        radix_mode = mode;
        
        // 启动变换
        @(posedge clk);
        start = 1;
        @(posedge clk);
        start = 0;
        
        // 等待变换完成
        wait(valid_out == 1);
        @(posedge clk);
        
        // 打印结果
        print_outputs(mode + 1);
        
        // 等待valid信号变低
        @(posedge clk);
        wait(valid_out == 0);
        @(posedge clk);
    end
    endtask
    
    // 主测试流程
    initial begin
        // 初始化
        clk = 0;
        rst_n = 0;
        init_inputs();
        
        // 复位
        #10 rst_n = 1;
        #10;
        
        $display("====================================");
        $display("Winograd Pre-Transform Testbench");
        $display("Modulus: %0d", modulus);
        $display("====================================");
        
        // 测试基2模式
        run_test(2'b00, "Radix-2");
        
        // 测试基4模式
        run_test(2'b01, "Radix-4");
        
        // 测试基8模式
        run_test(2'b10, "Radix-8");
        
        // 测试基16模式
        run_test(2'b11, "Radix-16");
        
        // 额外测试：测试模块空闲状态
        $display("=== Testing Idle State ===");
        #100;
        
        // 验证复位后的状态
        $display("=== Testing Reset ===");
        rst_n = 0;
        #10;
        rst_n = 1;
        #10;
        
        // 检查所有输出是否被清零
        for (integer i = 0; i < NUM_CORES; i = i + 1) begin
            if (x0_out[i] !== 0 || x1_out[i] !== 0 || w_out[i] !== 0 || conj_coeff_out[i] !== 0) begin
                $display("ERROR: Outputs not cleared after reset!");
                $finish;
            end
        end
        
        $display("=== All Tests Completed Successfully ===");
        $display("====================================");
        
        #100;
        $finish;
    end
    
    // 监视信号变化
    initial begin
        // 监视重要信号
        $monitor("Time=%0t: state=%d, valid=%b, radix_mode=%b", 
                 $time, dut.state, valid_out, radix_mode);
    end
    
    // 生成波形文件
    initial begin
        $dumpfile("winograd_pre_transform.vcd");
        $dumpvars(0, winograd_pre_transform_tb);
    end
    
endmodule

ntt_3_tfdg_full_twiddle_4_2_sum_axi_5/ntt_1/ntt_1.sim/sim_1/behav/xsim/winograd_pre_transform.vcd
$date
   Tue Jan 20 10:25:19 2026
$end
$version
  2019.1
$end
$timescale
  1ps
$end
$scope module winograd_pre_transform_tb $end
$var reg 1 ! clk $end
$var reg 1 " rst_n $end
$var reg 1 # start $end
$var reg 2 $ radix_mode [1:0] $end
$var reg 8 % modulus [7:0] $end
$var wire 1 & valid_out $end
$var parameter 32 ' MAX_WIDTH [31:0] $end
$var parameter 32 ( MAX_RADIX [31:0] $end
$var parameter 32 ) NUM_CORES [31:0] $end
$scope module dut $end
$var wire 1 * clk $end
$var wire 1 + rst_n $end
$var wire 1 , start $end
$var wire 2 - radix_mode [1:0] $end
$var wire 8 . modulus [7:0] $end
$var reg 1 / valid_out $end
$var reg 3 0 state [2:0] $end
$var parameter 32 1 MAX_WIDTH [31:0] $end
$var parameter 32 2 MAX_RADIX [31:0] $end
$var parameter 32 3 NUM_CORES [31:0] $end
$var parameter 3 4 IDLE [2:0] $end
$var parameter 3 5 CALC_GROUPS [2:0] $end
$var parameter 3 6 APPLY_TRANSFORM [2:0] $end
$var parameter 3 7 OUTPUT_READY [2:0] $end
$scope begin Block103_1 $end
$var integer 32 8 i $end
$upscope $end
$scope begin Block142_2 $end
$var integer 32 9 g $end
$scope begin Block142_3 $end
$var integer 32 : idx1 $end
$var integer 32 ; idx2 $end
$upscope $end
$upscope $end
$scope begin Block154_4 $end
$var integer 32 < g $end
$scope begin Block154_5 $end
$var integer 32 = idx1 $end
$var integer 32 > idx2 $end
$upscope $end
$upscope $end
$scope begin Block170_6 $end
$var integer 32 ? i $end
$upscope $end
$scope function mod_add $end
$var reg 8 @ mod_add [7:0] $end
$var reg 8 A a [7:0] $end
$var reg 8 B b [7:0] $end
$var reg 8 C mod [7:0] $end
$var reg 9 D sum [8:0] $end
$upscope $end
$scope function mod_sub $end
$var reg 8 @ mod_sub [7:0] $end
$var reg 8 A a [7:0] $end
$var reg 8 B b [7:0] $end
$var reg 8 C mod [7:0] $end
$var reg 8 E diff [7:0] $end
$upscope $end
$scope function calculate_conjugate $end
$var reg 8 @ calculate_conjugate [7:0] $end
$var reg 8 A w [7:0] $end
$var reg 8 B modulus [7:0] $end
$upscope $end
$scope function modular_inverse $end
$var reg 8 @ modular_inverse [7:0] $end
$var reg 8 A a [7:0] $end
$var reg 8 B modulus [7:0] $end
$var reg 8 C result [7:0] $end
$upscope $end
$upscope $end
$scope begin Block158_12 $end
$var integer 32 F i $end
$upscope $end
$scope task init_inputs $end
$scope begin Block60_8 $end
$var integer 32 G i $end
$upscope $end
$scope begin Block65_9 $end
$var integer 32 H i $end
$upscope $end
$upscope $end
$scope task print_outputs $end
$var integer 32 I test_num $end
$scope begin Block78_10 $end
$var integer 32 J i $end
$upscope $end
$upscope $end
$scope task run_test $end
$var reg 2 K mode [1:0] $end
$var reg 32 L mode_name $end
$upscope $end
$upscope $end
$enddefinitions $end
#0
$dumpvars
0!
0"
0#
b0 $
b10001 %
0&
b1000 '
b10000 (
b1000 )
0*
0+
0,
b0 -
b10001 .
0/
b0 0
b1000 1
b10000 2
b1000 3
b0 4
b1 5
b10 6
b11 7
b1000 8
bx 9
bx :
bx ;
bx <
bx =
bx >
bx ?
b0 @
b0 A
b0 B
b0 C
b0 D
b0 E
bx F
b10000 G
b1000 H
bx I
bx J
bx K
b0 L
$end
#5000
1!
1*
b1000 8
#10000
0!
1"
0*
1+
#15000
1!
1*
#20000
0!
b0 $
0*
b0 K
#25000
1!
1#
1*
1,
b1 0
#30000
0!
0*
#35000
1!
0#
1*
0,
b10 0
#40000
0!
0*
#45000
1!
1&
1*
1/
b11 0
b1000 ?
#50000
0!
0*
#55000
1!
0&
1*
0/
b0 0
b1 I
b1000 J
#60000
0!
0*
#65000
1!
1*
#70000
0!
0*
#75000
1!
b1 $
1*
b1 -
b1 K
#80000
0!
0*
#85000
1!
1#
1*
1,
b1 0
#90000
0!
0*
#95000
1!
0#
1*
0,
b10 0
#100000
0!
0*
#105000
1!
1&
1*
1/
b11 0
b1000 ?
#110000
0!
0*
#115000
1!
0&
1*
0/
b0 0
b10 I
b1000 J
#120000
0!
0*
#125000
1!
1*
#130000
0!
0*
#135000
1!
b10 $
1*
b10 -
b10 K
#140000
0!
0*
#145000
1!
1#
1*
1,
b1 0
#150000
0!
0*
#155000
1!
0#
1*
0,
b10 0
b100 9
b11 :
b100 ;
#160000
0!
0*
#165000
1!
1&
1*
1/
b11 0
b1000 ?
#170000
0!
0*
#175000
1!
0&
1*
0/
b0 0
b11 I
b1000 J
#180000
0!
0*
#185000
1!
1*
#190000
0!
0*
#195000
1!
b11 $
1*
b11 -
b11 K
#200000
0!
0*
#205000
1!
1#
1*
1,
b1 0
#210000
0!
0*
#215000
1!
0#
1*
0,
b10 0
b1000 <
b111 =
b1000 >
#220000
0!
0*
#225000
1!
1&
1*
1/
b11 0
b1000 ?
#230000
0!
0*
#235000
1!
0&
1*
0/
b0 0
b100 I
b1000 J
#240000
0!
0*
#245000
1!
1*
#250000
0!
0*
#255000
1!
1*
#260000
0!
0*
#265000
1!
1*
#270000
0!
0*
#275000
1!
1*
#280000
0!
0*
#285000
1!
1*
#290000
0!
0*
#295000
1!
1*
#300000
0!
0*
#305000
1!
1*
#310000
0!
0*
#315000
1!
1*
#320000
0!
0*
#325000
1!
1*
#330000
0!
0*
#335000
1!
1*
#340000
0!
0*
#345000
1!
1*
#350000
0!
0*
#355000
1!
0"
1*
0+
b1000 8
#360000
0!
0*
#365000
1!
1"
1*
1+
#370000
0!
0*
#375000
1!
1*
b1000 F
