NTT-accelerator-for-ZKP-0.4/ntt_3_tfdg_full_twiddle_4_2_sum_axi_5/sour/twiddle_dyn_gen_NTT/modular_multiplier_256bit.v
// modular_multiplier_256bit.v
`timescale 1ns / 1ps

module modular_multiplier_256bit #(
    parameter DATA_WIDTH = 256
)(
    input wire clk,
    input wire reset_n,
    input wire start,
    input wire [DATA_WIDTH-1:0] a,
    input wire [DATA_WIDTH-1:0] b,
    input wire [DATA_WIDTH-1:0] modulus,
    output reg [DATA_WIDTH-1:0] result,
    output reg done
);

// ================= 内部寄存器 =================
reg [2*DATA_WIDTH-1:0] product;  // 512位乘积
reg [DATA_WIDTH-1:0] a_reg, b_reg, modulus_reg;
reg [4:0] count;
reg busy;
reg [2:0] state;

// 使用Barrett约简的常数
localparam [DATA_WIDTH-1:0] MU = 256'h100000000000000000000000000000000;  // 2^(2*DATA_WIDTH) / modulus 的近似值

localparam IDLE    = 3'd0;
localparam MULT    = 3'd1;
localparam REDUCE  = 3'd2;
localparam FINISH  = 3'd3;

// ================= Barrett约简函数 =================
function [DATA_WIDTH-1:0] barrett_reduce;
    input [2*DATA_WIDTH-1:0] value;
    input [DATA_WIDTH-1:0] modulus;
    input [DATA_WIDTH-1:0] mu;
    reg [2*DATA_WIDTH-1:0] q_est;
    reg [2*DATA_WIDTH-1:0] reduced;
    integer i;  // 将 int 改为 integer
begin
    // Barrett约简算法：
    // 1. 计算 q_est = floor(value * mu / 2^{2n})
    // 2. 计算 r = value - q_est * modulus
    // 3. 如果 r >= modulus，则 r = r - modulus
    
    // 注意：这是简化版本，实际需要根据具体模数优化
    q_est = (value * mu) >> (2*DATA_WIDTH);
    reduced = value - q_est * modulus;
    
    // 可能需要多次减法（最多3次）
    for (i = 0; i < 3; i = i + 1) begin
        if (reduced >= modulus) begin
            reduced = reduced - modulus;
        end
    end
    
    barrett_reduce = reduced[DATA_WIDTH-1:0];
end
endfunction

// ================= 主状态机 =================
always @(posedge clk or negedge reset_n) begin
    if (!reset_n) begin
        state <= IDLE;
        result <= 0;
        done <= 0;
        count <= 0;
        busy <= 0;
        product <= 0;
        a_reg <= 0;
        b_reg <= 0;
        modulus_reg <= 0;
    end else begin
        done <= 0;
        
        case (state)
            IDLE: begin
                if (start && !busy) begin
                    a_reg <= a;
                    b_reg <= b;
                    modulus_reg <= modulus;
                    product <= 0;
                    count <= 0;
                    busy <= 1;
                    state <= MULT;
                    
                    $display("[%t] ModMult: Starting multiplication", $time);
                    $display("[%t] ModMult: a=%h, b=%h, modulus=%h", $time, a, b, modulus);
                end
            end
            
            MULT: begin
                // 多周期乘法（简化实现）
                // 实际中可能需要更高效的乘法算法
                if (count == 0) begin
                    // 计算乘积
                    product = a_reg * b_reg;
                    count <= count + 1;
                    state <= REDUCE;
                end
            end
            
/*             REDUCE: begin
                if (count == 1) begin
                    // 使用Barrett约简
                    result <= barrett_reduce(product, modulus_reg, MU);
                    count <= count + 1;
                    state <= FINISH;
                end
            end
 */ 
            REDUCE: begin
                if (count == 1) begin
                    // 特殊处理模数为0和1的情况
                    if (modulus_reg == 0) begin
                        // 模数为0，不进行模运算
                        result <= product[DATA_WIDTH-1:0];
                    end else if (modulus_reg == 1) begin
                        // 模数为1，任何数模1等于0
                        result <= 0;
                    end else begin
                        // 使用Barrett约简
                        result <= barrett_reduce(product, modulus_reg, MU);
                    end
                    count <= count + 1;
                    state <= FINISH;
                end
            end
 
            FINISH: begin
                done <= 1;
                busy <= 0;
                state <= IDLE;
                
                $display("[%t] ModMult: Result = %h", $time, result);
            end
            
            default: state <= IDLE;
        endcase
    end
end

endmodule

ntt_3_tfdg_full_twiddle_4_2_sum_axi_5/sour/twiddle_dyn_gen_NTT/modular_multiplier_tb.v
// modular_multiplier_tb.v
`timescale 1ns / 1ps

module modular_multiplier_tb;

// 参数
parameter DATA_WIDTH = 256;
parameter CLK_PERIOD = 10;

// 信号
reg clk;
reg reset_n;
reg start;
reg [DATA_WIDTH-1:0] a;
reg [DATA_WIDTH-1:0] b;
reg [DATA_WIDTH-1:0] modulus;
wire [DATA_WIDTH-1:0] result;
wire done;

// 测试控制
reg [7:0] test_num;
reg [31:0] cycle_count;

// 实例化
modular_multiplier_256bit dut (
    .clk(clk),
    .reset_n(reset_n),
    .start(start),
    .a(a),
    .b(b),
    .modulus(modulus),
    .result(result),
    .done(done)
);

// 时钟
initial begin
    clk = 0;
    forever #(CLK_PERIOD/2) clk = ~clk;
end

// 主测试
initial begin
    $display("==================================");
    $display("Modular Multiplier Test");
    $display("==================================");
    
    // 初始化
    initialize();
    
    // 测试1: 简单乘法
    test_num = 1;
    $display("\nTest %d: 2 * 3 mod 5 = 1", test_num);
    run_test(256'd2, 256'd3, 256'd5, 256'd1);
    
    // 测试2: 大数模运算
    test_num = test_num + 1;
    $display("\nTest %d: 16 * 32 mod 256 = 0", test_num);
    run_test(256'd16, 256'd32, 256'd256, 256'd0);
    
    // 测试3: 模数为0
    test_num = test_num + 1;
    $display("\nTest %d: 10 * 20 (mod 0) = 200", test_num);
    run_test(256'd10, 256'd20, 256'd0, 256'd200);
    
    // 测试4: 模数为1
    test_num = test_num + 1;
    $display("\nTest %d: 7 * 8 mod 1 = 0", test_num);
    run_test(256'd7, 256'd8, 256'd1, 256'd0);
    
    // 测试5: 零乘
    test_num = test_num + 1;
    $display("\nTest %d: 0 * 100 mod 50 = 0", test_num);
    run_test(256'd0, 256'd100, 256'd50, 256'd0);
    
    $display("\n==================================");
    $display("All tests completed");
    $display("==================================");
    
    #100;
    $finish;
end

// 初始化任务
task initialize;
begin
    reset_n = 0;
    start = 0;
    a = 0;
    b = 0;
    modulus = 0;
    test_num = 0;
    cycle_count = 0;
    
    #(CLK_PERIOD * 3);
    reset_n = 1;
    #(CLK_PERIOD * 2);
    
    $display("[%0t] Initialized", $time);
end
endtask

// 运行单个测试
task run_test;
    input [DATA_WIDTH-1:0] a_val;
    input [DATA_WIDTH-1:0] b_val;
    input [DATA_WIDTH-1:0] mod_val;
    input [DATA_WIDTH-1:0] exp_val;
    
    integer timeout;
    integer start_time;
begin
    // 设置输入
    a = a_val;
    b = b_val;
    modulus = mod_val;
    
    #(CLK_PERIOD);
    
    // 启动计算
    start_time = $time;
    start = 1;
    #(CLK_PERIOD);
    start = 0;
    
    // 等待完成
    timeout = 0;
    while (done == 0 && timeout < 100) begin
        #(CLK_PERIOD);
        timeout = timeout + 1;
    end
    
    // 检查结果
    if (done == 1) begin
        if (result === exp_val) begin
            $display("[%0t] PASS: Got %h", $time, result);
        end else begin
            $display("[%0t] FAIL: Got %h, Expected %h", $time, result, exp_val);
        end
        $display("    Time: %d cycles", ($time - start_time)/CLK_PERIOD);
    end else begin
        $display("[%0t] TIMEOUT", $time);
    end
    
    // 等待几个周期
    #(CLK_PERIOD * 5);
end
endtask

// 时钟计数
always @(posedge clk) begin
    cycle_count <= cycle_count + 1;
end

// 监视器
always @(posedge clk) begin
    if (done) begin
        $display("[%0t] Multiplier done: %h", $time, result);
    end
end

// 波形记录
initial begin
    $dumpfile("modmult_tb.vcd");
    $dumpvars(0, modular_multiplier_tb);
end

// 超时保护
initial begin
    #(10000);
    $display("\n[%0t] Simulation timeout", $time);
    $finish;
end

endmodule

NTT-accelerator-for-ZKP-0.4/ntt_3_tfdg_full_twiddle_4_2_sum_axi_5/ntt_1/ntt_1.sim/sim_1/behav/xsim/modmult_tb.vcd
$date
   Fri Jan  2 17:45:19 2026
$end
$version
  2019.1
$end
$timescale
  1ps
$end
$scope module modular_multiplier_tb $end
$var reg 1 ! clk $end
$var reg 1 " reset_n $end
$var reg 1 # start $end
$var reg 256 $ a [255:0] $end
$var reg 256 % b [255:0] $end
$var reg 256 & modulus [255:0] $end
$var wire 256 ' result [255:0] $end
$var wire 1 ( done $end
$var reg 8 ) test_num [7:0] $end
$var reg 32 * cycle_count [31:0] $end
$var parameter 32 + DATA_WIDTH [31:0] $end
$var parameter 32 , CLK_PERIOD [31:0] $end
$scope module dut $end
$var wire 1 - clk $end
$var wire 1 . reset_n $end
$var wire 1 / start $end
$var wire 256 0 a [255:0] $end
$var wire 256 1 b [255:0] $end
$var wire 256 2 modulus [255:0] $end
$var reg 256 3 result [255:0] $end
$var reg 1 4 done $end
$var reg 512 5 product [511:0] $end
$var reg 256 6 a_reg [255:0] $end
$var reg 256 7 b_reg [255:0] $end
$var reg 256 8 modulus_reg [255:0] $end
$var reg 5 9 count [4:0] $end
$var reg 1 : busy $end
$var reg 3 ; state [2:0] $end
$var parameter 32 < DATA_WIDTH [31:0] $end
$var parameter 256 = MU [255:0] $end
$var parameter 3 > IDLE [2:0] $end
$var parameter 3 ? MULT [2:0] $end
$var parameter 3 @ REDUCE [2:0] $end
$var parameter 3 A FINISH [2:0] $end
$scope function barrett_reduce $end
$var reg 256 B barrett_reduce [255:0] $end
$var reg 512 C value [511:0] $end
$var reg 256 D modulus [255:0] $end
$var reg 256 E mu [255:0] $end
$var reg 512 F q_est [511:0] $end
$var reg 512 G reduced [511:0] $end
$var integer 32 H i $end
$upscope $end
$upscope $end
$scope task initialize $end
$upscope $end
$scope task run_test $end
$var reg 256 I a_val [255:0] $end
$var reg 256 J b_val [255:0] $end
$var reg 256 K mod_val [255:0] $end
$var reg 256 L exp_val [255:0] $end
$var integer 32 M timeout $end
$var integer 32 N start_time $end
$upscope $end
$upscope $end
$enddefinitions $end
#0
$dumpvars
0!
0"
0#
b0 $
b0 %
b0 &
b0 '
0(
b0 )
b0 *
b100000000 +
b1010 ,
0-
0.
0/
b0 0
b0 1
b0 2
b0 3
04
b0 5
b0 6
b0 7
b0 8
b0 9
0:
b0 ;
b100000000 <
b100000000000000000000000000000000000000000000000000000000000000000000000000000000000000000000000000000000000000000000000000000000 =
b0 >
b1 ?
b10 @
b11 A
bx B
bx C
bx D
bx E
bx F
bx G
bx H
bx I
bx J
bx K
bx L
bx M
bx N
$end
#5000
1!
b1 *
1-
#10000
0!
0-
#15000
1!
b10 *
1-
#20000
0!
0-
#25000
1!
b11 *
1-
#30000
0!
1"
0-
1.
#35000
1!
b100 *
1-
#40000
0!
0-
#45000
1!
b101 *
1-
#50000
0!
b10 $
b11 %
b101 &
b1 )
0-
b10 0
b11 1
b101 2
b10 I
b11 J
b101 K
b1 L
#55000
1!
b110 *
1-
#60000
0!
1#
0-
1/
b111100 N
#65000
1!
b111 *
1-
b10 6
b11 7
b101 8
1:
b1 ;
#70000
0!
0#
0-
0/
b0 M
#75000
1!
b1000 *
1-
b110 5
b1 9
b10 ;
#80000
0!
0-
b1 M
#85000
1!
b1 '
b1001 *
1-
b1 3
b10 9
b11 ;
b1 B
b110 C
b101 D
b100000000000000000000000000000000000000000000000000000000000000000000000000000000000000000000000000000000000000000000000000000000 E
b0 F
b1 G
b11 H
#90000
0!
0-
b10 M
#95000
1!
1(
b1010 *
1-
14
0:
b0 ;
#100000
0!
0-
b11 M
#105000
1!
0(
b1011 *
1-
04
#110000
0!
0-
#115000
1!
b1100 *
1-
#120000
0!
0-
#125000
1!
b1101 *
1-
#130000
0!
0-
#135000
1!
b1110 *
1-
#140000
0!
0-
#145000
1!
b1111 *
1-
#150000
0!
b10000 $
b100000 %
b100000000 &
b10 )
0-
b10000 0
b100000 1
b100000000 2
b10000 I
b100000 J
b100000000 K
b0 L
#155000
1!
b10000 *
1-
#160000
0!
1#
0-
1/
b10100000 N
#165000
1!
b10001 *
1-
b0 5
b10000 6
b100000 7
b100000000 8
b0 9
1:
b1 ;
#170000
0!
0#
0-
0/
b0 M
#175000
1!
b10010 *
1-
b1000000000 5
b1 9
b10 ;
#180000
0!
0-
b1 M
#185000
1!
b0 '
b10011 *
1-
b0 3
b10 9
b11 ;
b0 B
b1000000000 C
b100000000 D
b0 G
b11 H
#190000
0!
0-
b10 M
#195000
1!
1(
b10100 *
1-
14
0:
b0 ;
#200000
0!
0-
b11 M
#205000
1!
0(
b10101 *
1-
04
#210000
0!
0-
#215000
1!
b10110 *
1-
#220000
0!
0-
#225000
1!
b10111 *
1-
#230000
0!
0-
#235000
1!
b11000 *
1-
#240000
0!
0-
#245000
1!
b11001 *
1-
#250000
0!
b1010 $
b10100 %
b0 &
b11 )
0-
b1010 0
b10100 1
b0 2
b1010 I
b10100 J
b0 K
b11001000 L
#255000
1!
b11010 *
1-
#260000
0!
1#
0-
1/
b100000100 N
#265000
1!
b11011 *
1-
b0 5
b1010 6
b10100 7
b0 8
b0 9
1:
b1 ;
#270000
0!
0#
0-
0/
b0 M
#275000
1!
b11100 *
1-
b11001000 5
b1 9
b10 ;
#280000
0!
0-
b1 M
#285000
1!
b11001000 '
b11101 *
1-
b11001000 3
b10 9
b11 ;
#290000
0!
0-
b10 M
#295000
1!
1(
b11110 *
1-
14
0:
b0 ;
#300000
0!
0-
b11 M
#305000
1!
0(
b11111 *
1-
04
#310000
0!
0-
#315000
1!
b100000 *
1-
#320000
0!
0-
#325000
1!
b100001 *
1-
#330000
0!
0-
#335000
1!
b100010 *
1-
#340000
0!
0-
#345000
1!
b100011 *
1-
#350000
0!
b111 $
b1000 %
b1 &
b100 )
0-
b111 0
b1000 1
b1 2
b111 I
b1000 J
b1 K
b0 L
#355000
1!
b100100 *
1-
#360000
0!
1#
0-
1/
b101101000 N
#365000
1!
b100101 *
1-
b0 5
b111 6
b1000 7
b1 8
b0 9
1:
b1 ;
#370000
0!
0#
0-
0/
b0 M
#375000
1!
b100110 *
1-
b111000 5
b1 9
b10 ;
#380000
0!
0-
b1 M
#385000
1!
b0 '
b100111 *
1-
b0 3
b10 9
b11 ;
#390000
0!
0-
b10 M
#395000
1!
1(
b101000 *
1-
14
0:
b0 ;
#400000
0!
0-
b11 M
#405000
1!
0(
b101001 *
1-
04
#410000
0!
0-
#415000
1!
b101010 *
1-
#420000
0!
0-
#425000
1!
b101011 *
1-
#430000
0!
0-
#435000
1!
b101100 *
1-
#440000
0!
0-
#445000
1!
b101101 *
1-
#450000
0!
b0 $
b1100100 %
b110010 &
b101 )
0-
b0 0
b1100100 1
b110010 2
b0 I
b1100100 J
b110010 K
#455000
1!
b101110 *
1-
#460000
0!
1#
0-
1/
b111001100 N
#465000
1!
b101111 *
1-
b0 5
b0 6
b1100100 7
b110010 8
b0 9
1:
b1 ;
#470000
0!
0#
0-
0/
b0 M
#475000
1!
b110000 *
1-
b1 9
b10 ;
#480000
0!
0-
b1 M
#485000
1!
b110001 *
1-
b10 9
b11 ;
b0 C
b110010 D
b11 H
#490000
0!
0-
b10 M
#495000
1!
1(
b110010 *
1-
14
0:
b0 ;
#500000
0!
0-
b11 M
#505000
1!
0(
b110011 *
1-
04
#510000
0!
0-
#515000
1!
b110100 *
1-
#520000
0!
0-
#525000
1!
b110101 *
1-
#530000
0!
0-
#535000
1!
b110110 *
1-
#540000
0!
0-
#545000
1!
b110111 *
1-
#550000
0!
0-
#555000
1!
b111000 *
1-
#560000
0!
0-
#565000
1!
b111001 *
1-
#570000
0!
0-
#575000
1!
b111010 *
1-
#580000
0!
0-
#585000
1!
b111011 *
1-
#590000
0!
0-
#595000
1!
b111100 *
1-
#600000
0!
0-
#605000
1!
b111101 *
1-
#610000
0!
0-
#615000
1!
b111110 *
1-
#620000
0!
0-
#625000
1!
b111111 *
1-
#630000
0!
0-
#635000
1!
b1000000 *
1-
#640000
0!
0-
#645000
1!
b1000001 *
1-
